{"cameraMode":{"drawMode":0,"name":"Shaded","section":"Shading Mode"},"sceneLighting":true,"audioPlay":false,"sceneViewState":{"m_AlwaysRefresh":false,"showFog":true,"showSkybox":true,"showFlares":true,"showImageEffects":true,"showParticleSystems":true,"showVisualEffectGraphs":true,"m_FxEnabled":true},"in2DMode":false,"pivot":{"x":-2.333369493484497,"y":-0.7670674324035645,"z":0.8191080093383789},"rotation":{"x":-0.33501136302948,"y":0.4162101447582245,"z":-0.16832304000854493,"w":-0.8283772468566895},"size":7.054511070251465,"orthographic":false}